redsession/__init__.py
redsession/middleware.py
redsession/backend/__init__.py
redsession/backend/base.py
redsession/backend/redis.py
redsession-1.4.0.dist-info/METADATA
redsession-1.4.0.dist-info/WHEEL
redsession-1.4.0.dist-info/licenses/LICENSE.md
redsession-1.4.0.dist-info/RECORD
