Metadata-Version: 2.3
Name: redsession
Version: 1.4.0
Summary: Simple and fast server session middleware for FastAPI and Starlette
Project-URL: Repository, https://github.com/TheJecksMan/red-session
Project-URL: Issues, https://github.com/TheJecksMan/red-session/issues
Project-URL: Docs, https://red-session.readthedocs.io/en/stable/
Author: TheJecksMan
License-Expression: MIT
License-File: LICENSE.md
Classifier: Framework :: FastAPI
Classifier: License :: OSI Approved :: MIT License
Classifier: Operating System :: OS Independent
Classifier: Programming Language :: Python
Classifier: Programming Language :: Python :: 3
Classifier: Programming Language :: Python :: 3 :: Only
Classifier: Programming Language :: Python :: 3.8
Classifier: Programming Language :: Python :: 3.9
Classifier: Programming Language :: Python :: 3.10
Classifier: Programming Language :: Python :: 3.11
Classifier: Programming Language :: Python :: 3.12
Requires-Python: >=3.8
Requires-Dist: itsdangerous>=2.1.2
Requires-Dist: redis<6.0.0,>=5.0.0
Requires-Dist: starlette>=0.36.3
Provides-Extra: opt
Requires-Dist: orjson>=3.9.0; extra == 'opt'
Requires-Dist: redis[hiredis]<6.0.0,>=5.0.0; extra == 'opt'
